{
  "project_info": {
    "project_number": "496874591906",
    "project_id": "evens-2f983",
    "storage_bucket": "evens-2f983.firebasestorage.app"
  },
  "client": [
    {
      "client_info": {
        "mobilesdk_app_id": "1:496874591906:android:c8e7ac3404c7cffb06e9fb",
        "android_client_info": {
          "package_name": "app.temsah.tabibak_for_clinic"
        }
      },
      "oauth_client": [],
      "api_key": [
        {
          "current_key": "AIzaSyCkhwBWe3CAr0TLWM01La5epQYH_HXouWU"
        }
      ],
      "services": {
        "appinvite_service": {
          "other_platform_oauth_client": []
        }
      }
    }
  ],
  "configuration_version": "1"
}